Bitcoin_notification/__init__.py
Bitcoin_notification/bitcoin_notifications.py
Bitcoin_notification/notification.py
Bitcoin_notifications_karishma_agarwal_21-0.0.5.dist-info/LICENSE.rtf
Bitcoin_notifications_karishma_agarwal_21-0.0.5.dist-info/METADATA
Bitcoin_notifications_karishma_agarwal_21-0.0.5.dist-info/WHEEL
Bitcoin_notifications_karishma_agarwal_21-0.0.5.dist-info/top_level.txt
Bitcoin_notifications_karishma_agarwal_21-0.0.5.dist-info/RECORD
