Metadata-Version: 2.1
Name: Bitcoin-notifications-karishma-agarwal-21
Version: 0.0.5
Summary: A small project for bitcoin price notifications
Home-page: https://github.com/karishma-garg-au7/bitcoin_notification
Author: Karishma Agarwal
Author-email: karishmaag21@gmail.com
License: UNKNOWN
Platform: UNKNOWN
Classifier: Programming Language :: Python :: 3
Classifier: License :: OSI Approved :: MIT License
Classifier: Operating System :: OS Independent
Requires-Python: >=3.6
